yapocl/__init__.py
yapocl/ad.py
yapocl/bd.py
yapocl/image.py
yapocl/blocket/__init__.py
yapocl/blocket/ad.py
yapocl/blocket/bd.py
yapocl/blocket/image.py
yapocl/datawarehouse/__init__.py
yapocl/datawarehouse/bd.py
yapocl-0.0.9.dist-info/LICENSE.txt
yapocl-0.0.9.dist-info/METADATA
yapocl-0.0.9.dist-info/WHEEL
yapocl-0.0.9.dist-info/top_level.txt
yapocl-0.0.9.dist-info/RECORD
